gcid/__init__.py
gcid/clocked.py
gcid/handler.py
gcid/objects.py
gcid/persist.py
gcid/threads.py
gcid/modules/__init__.py
gcid/modules/cmd.py
gcid/modules/dbg.py
gcid/modules/flt.py
gcid/modules/irc.py
gcid/modules/log.py
gcid/modules/mdl.py
gcid/modules/req.py
gcid/modules/rss.py
gcid/modules/sts.py
gcid/modules/tdo.py
gcid/modules/thr.py
gcid/modules/upt.py
gcid/modules/utility.py
gcid/modules/wsd.py
gcid-160.data/data/gcid/gcid.service
gcid-160.data/data/share/doc/gcid/ECHAabilify.png
gcid-160.data/data/share/doc/gcid/ECHAclozapine.png
gcid-160.data/data/share/doc/gcid/ECHAhaldol.png
gcid-160.data/data/share/doc/gcid/ECHAzyprexa.png
gcid-160.data/data/share/doc/gcid/EM_T04_OTP-CR-117_19.pdf
gcid-160.data/data/share/doc/gcid/EM_T07_OTP-CR-117_19_001.pdf
gcid-160.data/data/share/doc/gcid/Kamer.pdf
gcid-160.data/data/share/doc/gcid/OTP1.png
gcid-160.data/data/share/doc/gcid/OTP2.png
gcid-160.data/data/share/doc/gcid/about.rst
gcid-160.data/data/share/doc/gcid/base.rst
gcid-160.data/data/share/doc/gcid/bevestigd.jpg
gcid-160.data/data/share/doc/gcid/bevestigd.pdf
gcid-160.data/data/share/doc/gcid/class.rst
gcid-160.data/data/share/doc/gcid/conf.py
gcid-160.data/data/share/doc/gcid/evidence.rst
gcid-160.data/data/share/doc/gcid/gcid.css
gcid-160.data/data/share/doc/gcid/genocide.png
gcid-160.data/data/share/doc/gcid/guilty.rst
gcid-160.data/data/share/doc/gcid/index.rst
gcid-160.data/data/share/doc/gcid/informed.jpg
gcid-160.data/data/share/doc/gcid/kamer.png
gcid-160.data/data/share/doc/gcid/manual.rst
gcid-160.data/data/share/doc/gcid/module.rst
gcid-160.data/data/share/doc/gcid/reconsider.rst
gcid-160.data/data/share/doc/gcid/request.rst
gcid-160.data/data/share/doc/gcid/requirements.txt
gcid-160.data/data/share/doc/gcid/skull.jpg
gcid-160.data/data/share/doc/gcid/skull3.png
gcid-160.data/data/share/doc/gcid/skull4.png
gcid-160.data/data/share/doc/gcid/skullagain.jpg
gcid-160.data/data/share/doc/gcid/source.rst
gcid-160.data/data/share/doc/gcid/writings.rst
gcid-160.dist-info/METADATA
gcid-160.dist-info/WHEEL
gcid-160.dist-info/top_level.txt
gcid-160.dist-info/zip-safe
gcid-160.dist-info/RECORD
