Metadata-Version: 2.1
Name: gcid
Version: 160
Summary: poison law genocide
Home-page: https://github.com/bthate/gcid
Author: Bart Thate
Author-email: thatebhj@gmail.com
License: Public Domain
Platform: UNKNOWN
Classifier: Development Status :: 3 - Alpha
Classifier: License :: Public Domain
Classifier: Operating System :: Unix
Classifier: Programming Language :: Python
Classifier: Topic :: Utilities
